triprint/__init__.py
triprint-1.0.5.dist-info/METADATA
triprint-1.0.5.dist-info/WHEEL
triprint-1.0.5.dist-info/license
triprint-1.0.5.dist-info/top_level.txt
triprint-1.0.5.dist-info/RECORD
