Metadata-Version: 2.1
Name: triprint
Version: 1.0.5
Summary: This package is created by Vikrant Singh. This package is used for printing '*' or '#' triangles for desired number of rows.
Home-page: https://github.com/vikrantsingh298/Vikrant-s-Stuff/blob/master/triangle_print.py
Author: Vikrant Singh
Author-email: vikrants298@gmail.com
License: MIT
Platform: UNKNOWN
